training/__init__.py
training/admin.py
training/apps.py
training/forms.py
training/models.py
training/schor_url.py
training/tests.py
training/urls.py
training/utils.py
training/views.py
training/api/urls.py
training/api/views.py
training/api/__pycache__/urls.cpython-310.pyc
training/api/__pycache__/urls.cpython-37.pyc
training/api/__pycache__/views.cpython-310.pyc
training/api/__pycache__/views.cpython-37.pyc
training/migrations/0001_initial.py
training/migrations/0002_hrcriteria_trainingemp_tyear_unitcriteria_and_more.py
training/migrations/0003_rename_fundtype_ttype_delete_trainingtype_and_more.py
training/migrations/0004_trainingplan_duration.py
training/migrations/0005_tcriteria_trainingcriteria_remove_unitcriteria_plan_and_more.py
training/migrations/0006_alter_tcriteria_subject.py
training/migrations/0007_trainingplan_is_approve_trainingplan_is_certify_and_more.py
training/migrations/0008_trainingsubject.py
training/migrations/0009_remove_trainingplan_duration_and_more.py
training/migrations/0010_trainingplan_duration_trainingplan_place_and_more.py
training/migrations/0011_remove_trainingemp_hashed_delete_trainingsubject.py
training/migrations/0012_trainingemp_diploma_alter_trainingemp_department_and_more.py
training/migrations/0013_alter_trainingcriteria_criteria.py
training/migrations/0014_tcriteria_is_active.py
training/migrations/0015_auto_20221210_0226.py
training/migrations/0016_trainingemp_is_update.py
training/migrations/0017_scholarshipplan_sprogress_stype.py
training/migrations/0018_auto_20221210_1435.py
training/migrations/0019_scholarshipemp_scholarshipempprogress.py
training/migrations/0020_auto_20221210_1550.py
training/migrations/0021_rename_start_date_scholarshipempprogress_date.py
training/migrations/0022_alter_scholarshipemp_emp.py
training/migrations/0023_scholarshipplan_is_update.py
training/migrations/0024_auto_20221210_1742.py
training/migrations/0025_trainingemp_subject.py
training/migrations/0026_traininggap.py
django_ipghrms_training-1.2.dist-info/LICENSE
django_ipghrms_training-1.2.dist-info/METADATA
django_ipghrms_training-1.2.dist-info/WHEEL
django_ipghrms_training-1.2.dist-info/top_level.txt
django_ipghrms_training-1.2.dist-info/RECORD
